snsedextend/BIC.py
snsedextend/__init__.py
snsedextend/bb.py
snsedextend/cc_extrap.py
snsedextend/colorCalc.py
snsedextend/example.py
snsedextend/helpers.py
snsedextend/ia_extrap.py
snsedextend/spec.py
snsedextend/utils.py
snsedextend/data/.DS_Store
snsedextend/data/bands/bBand/tophatB.dat
snsedextend/data/bands/hBand/f160w.dat
snsedextend/data/bands/hBand/paritelH.dat
snsedextend/data/bands/hBand/tophatH.dat
snsedextend/data/bands/iBand/tophatI.dat
snsedextend/data/bands/jBand/f125w.dat
snsedextend/data/bands/jBand/paritelJ.dat
snsedextend/data/bands/jBand/tophatJ.dat
snsedextend/data/bands/jBand/tophatJ.dat~
snsedextend/data/bands/kBand/paritelKs.dat
snsedextend/data/bands/kBand/tophatK.dat
snsedextend/data/bands/rBand/tophatR.dat
snsedextend/data/bands/uBand/tophatU.dat
snsedextend/data/bands/vBand/tophatV.dat
snsedextend/data/default/.DS_Store
snsedextend/data/default/NON1A.LIST
snsedextend/data/default/NON1A.LIST~
snsedextend/data/default/typeII/IIColors.dat
snsedextend/data/default/typeII/IICurve.pick
snsedextend/data/default/typeII/II_aveSpec.dat
snsedextend/data/default/typeIa/Ia_aveSpec.dat
snsedextend/data/default/typeIb/IbColors.dat
snsedextend/data/default/typeIb/IbCurve.pick
snsedextend/data/default/typeIb/Ib_aveSpec.dat
snsedextend/data/default/typeIc/IcColors.dat
snsedextend/data/default/typeIc/IcCurve.pick
snsedextend/data/default/typeIc/Ic_aveSpec.dat
snsedextend/data/salt2-4/SALT2.INFO
snsedextend/data/salt2-4/salt2_color_correction.dat
snsedextend/data/salt2-4/salt2_color_dispersion.dat
snsedextend/data/salt2-4/salt2_lc_dispersion_scaling.dat
snsedextend/data/salt2-4/salt2_lc_relative_covariance_01.dat
snsedextend/data/salt2-4/salt2_lc_relative_variance_0.dat
snsedextend/data/salt2-4/salt2_lc_relative_variance_1.dat
snsedextend/data/salt2-4/salt2_spec_covariance_01.dat
snsedextend/data/salt2-4/salt2_spec_variance_0.dat
snsedextend/data/salt2-4/salt2_spec_variance_1.dat
snsedextend/data/salt2-4/salt2_template_0.dat
snsedextend-0.3.7.dist-info/METADATA
snsedextend-0.3.7.dist-info/WHEEL
snsedextend-0.3.7.dist-info/top_level.txt
snsedextend-0.3.7.dist-info/RECORD
