Metadata-Version: 2.1
Name: snsedextend
Version: 0.3.7
Summary: UNKNOWN
Home-page: UNKNOWN
Author: J. R. Pierel
Author-email: jr23@email.sc.edu
License: UNKNOWN
Platform: UNKNOWN
Requires-Dist: cython
Requires-Dist: numpy
Requires-Dist: scipy
Requires-Dist: sncosmo (>=1.5)
Requires-Dist: astropy
Requires-Dist: matplotlib
Requires-Dist: pandas
Requires-Dist: pymc3 (>=3.0)
Requires-Dist: pyParz (>=0.0.3)
Requires-Dist: iminuit
Requires-Dist: theano
